spectralETD/__init__.py
spectralETD/spectralETD.py
spectralETD/volumerender.py
spectraletd-0.0.4.dist-info/licenses/LICENSE.txt
spectraletd-0.0.4.dist-info/METADATA
spectraletd-0.0.4.dist-info/WHEEL
spectraletd-0.0.4.dist-info/top_level.txt
spectraletd-0.0.4.dist-info/RECORD
