Metadata-Version: 2.4
Name: spectralETD
Version: 0.0.4
Summary: A Python Implementation of combining Exponential Time Differencing and Pseudo-spectral Methods for Phase-Field Model Equation
Author-email: Elvis Soares <elvis.asoares@gmail.com>
Project-URL: Documentation, https://spectraletd.readthedocs.io
Project-URL: Homepage, https://github.com/elvissoares/spectralETD
Keywords: python,torch,gpu,phase-field
Classifier: Development Status :: 2 - Pre-Alpha
Classifier: Intended Audience :: Science/Research
Classifier: License :: OSI Approved :: MIT License
Classifier: Programming Language :: Python :: 3
Classifier: Programming Language :: Python :: Implementation
Classifier: Topic :: Scientific/Engineering :: Physics
Classifier: Topic :: Scientific/Engineering :: Chemistry
Classifier: Topic :: Scientific/Engineering :: Mathematics
Classifier: Environment :: GPU
Requires-Python: >=3.10
License-File: LICENSE.txt
Dynamic: license-file
